[
  {
    "AwayImage": "https://i.ibb.co/T12PsPR/download-3.png",
    "AwayName": "Liverpool",
    "Date": "July 30",
    "Link": [
  {
   "type": "Highlight",
   "quality": "720P",
   "link": "https://hooo.topravideo.com:443/UpFiles/2023/7/30/42/259538/ 720p.m3u8"
  },
  {
   "type": "Highlight",
   "quality": "360P",
   "link": "https://hooo.topravideo.com:443/UpFiles/2023/7/30/42/259538/ 360p.m3u8"
  }
             ],
    "HomeImage": "https://i.ibb.co/V3Rk4tH/download-14.png",
    "HomeName": "Leicester City",
    "Hot": "Hot",
    "LeagueImage": "https://www.flashscore.com/res/image/data/jiylaOkD-fHcB8pl5.png",
    "LeagueName": "Club Club Friendly",
    "LiveUpcoming": "Upcoming",
    "Time": "0 - 4"
  },
  {
    "AwayImage": "https://i.ibb.co/NV6t3Ck/download-39.png",
    "AwayName": "Atletico Madrid",
    "Date": "July 30",
    "Link": [
  {
   "type": "Highlight",
   "quality": "720P",
   "link": "https://hooo.topravideo.com:443/UpFiles/2023/7/30/42/259560/ 720p.m3u8"
  },
  {
   "type": "Highlight",
   "quality": "360P",
   "link": "https://hooo.topravideo.com:443/UpFiles/2023/7/30/42/259560/ 360p.m3u8"
  }
             ],
    "HomeImage": "https://i.ibb.co/v4DMkVK/download-2.png",
    "HomeName": "Manchester City",
    "Hot": "Hot",
    "LeagueImage": "https://www.flashscore.com/res/image/data/jiylaOkD-fHcB8pl5.png",
    "LeagueName": "Club Club Friendly",
    "LiveUpcoming": "Upcoming",
    "Time": "1 - 2"
  },
  {
    "AwayImage": "https://i.ibb.co/gzBVDwK/download-18.png",
    "AwayName": "Brentford",
    "Date": "July 30",
    "Link": [
  {
   "type": "Highlight",
   "quality": "720P",
   "link": "https://hooo.topravideo.com:443/UpFiles/2023/7/30/42/259606/ 720p.m3u8"
  },
  {
   "type": "Highlight",
   "quality": "360P",
   "link": "https://hooo.topravideo.com:443/UpFiles/2023/7/30/42/259606/ 360p.m3u8"
  }
             ],
    "HomeImage": "https://i.ibb.co/wK5L6HX/download-8.png",
    "HomeName": "Aston Villa",
    "Hot": "Hot",
    "LeagueImage": "https://www.flashscore.com/res/image/data/jiylaOkD-fHcB8pl5.png",
    "LeagueName": "Club Friendly",
    "LiveUpcoming": "Upcoming",
    "Time": "3 - 3"
  },
  {
    "AwayImage": "https://i.ibb.co/8YZYVzF/download-15.png",
    "AwayName": "Fulham",
    "Date": "July 31",
    "Link": [
  {
   "type": "Highlight",
   "quality": "720P",
   "link": "https://hooo.topravideo.com:443/UpFiles/2023/7/30/42/259626/ 720p.m3u8"
  },
  {
   "type": "Highlight",
   "quality": "360P",
   "link": "https://hooo.topravideo.com:443/UpFiles/2023/7/30/42/259626/ 360p.m3u8"
  }
             ],
    "HomeImage": "https://i.ibb.co/MMN9Rw5/download.png",
    "HomeName": "Chelsea",
    "Hot": "Hot",
    "LeagueImage": "https://www.flashscore.com/res/image/data/jiylaOkD-fHcB8pl5.png",
    "LeagueName": "Club Friendly",
    "LiveUpcoming": "Upcoming",
    "Time": "2 - 0"
  },
  {
    "AwayImage": "https://i.ibb.co/L6tK4v1/download-77.png",
    "AwayName": "Dortmund",
    "Date": "July 31",
    "Link": [
  {
   "type": "Highlight",
   "quality": "720P",
   "link": "https://hooo.topravideo.com:443/UpFiles/2023/7/31/42/259640/ 720p.m3u8"
  },
  {
   "type": "Highlight",
   "quality": "360P",
   "link": "https://hooo.topravideo.com:443/UpFiles/2023/7/31/42/259640/ 360p.m3u8"
  }
             ],
    "HomeImage": "https://i.ibb.co/rZFH50R/download-1.png",
    "HomeName": "Manchester United",
    "Hot": "Hot",
    "LeagueImage": "https://www.flashscore.com/res/image/data/jiylaOkD-fHcB8pl5.png",
    "LeagueName": "Club Friendly",
    "LiveUpcoming": "Upcoming",
    "Time": "2 - 3"
  },
  {
    "AwayImage": "https://i.ibb.co/jh44yWL/download-66.png",
    "AwayName": "Barcelona",
    "Date": "July 27",
    "Link": [
  {
   "type": "Highlight",
   "quality": "HD",
   "link": "https://m.topravideo.com/UpFiles/2023/7/27/42/259303/720p.m3u8"
  },
  {
   "type": "Highlight",
   "quality": "SD",
   "link": "https://m.topravideo.com/UpFiles/2023/7/27/42/259303/360p.m3u8"
  }
             ],
    "HomeImage": "https://i.ibb.co/bN749H2/download-12.png",
    "HomeName": "Arsenal",
    "Hot": "Hot",
    "LeagueImage": "https://www.flashscore.com/res/image/data/jiylaOkD-fHcB8pl5.png",
    "LeagueName": "Club Friendly",
    "LiveUpcoming": "Upcoming",
    "Time": "5 - 3"
  },
  {
    "AwayImage": "https://i.ibb.co/McsHxxG/download-4.png",
    "AwayName": "Newcastle",
    "Date": "July 27",
    "Link": [
  {
   "type": "Highlight",
   "quality": "HD",
   "link": "https://m.topravideo.com:443/UpFiles/2023/7/27/42/259283/ 720p.m3u8"
  },
  {
   "type": "Highlight",
   "quality": "SD",
   "link": "https://m.topravideo.com:443/UpFiles/2023/7/27/42/259283/ 360p.m3u8"
  }
             ],
    "HomeImage": "https://i.ibb.co/MMN9Rw5/download.png",
    "HomeName": "Chelsea",
    "Hot": "Hot",
    "LeagueImage": "https://www.flashscore.com/res/image/data/jiylaOkD-fHcB8pl5.png",
    "LeagueName": "Club Friendly",
    "LiveUpcoming": "Upcoming",
    "Time": "1 - 1"
  },
  {
    "AwayImage": "https://i.ibb.co/N27SsT5/download-35.png",
    "AwayName": "Real Madrid",
    "Date": "July 27",
    "Link": [
  {
   "type": "Highlight",
   "quality": "HD",
   "link": "https://m.topravideo.com:443/UpFiles/2023/7/27/42/259287/ 720p.m3u8"
  },
  {
   "type": "Highlight",
   "quality": "SD",
   "link": "https://m.topravideo.com:443/UpFiles/2023/7/27/42/259287/ 360p.m3u8"
  }
             ],
    "HomeImage": "https://i.ibb.co/rZFH50R/download-1.png",
    "HomeName": "Manchester United",
    "Hot": "Hot",
    "LeagueImage": "https://www.flashscore.com/res/image/data/jiylaOkD-fHcB8pl5.png",
    "LeagueName": "Club Friendly",
    "LiveUpcoming": "Upcoming",
    "Time": "0 - 2"
  },
  {
    "AwayImage": "https://i.ibb.co/v4DMkVK/download-2.png",
    "AwayName": "Manchester City",
    "Date": "July 26",
    "Link": [
  {
   "type": "Highlight",
   "quality": "HD",
   "link": "https://m.topravideo.com:443/UpFiles/2023/7/26/42/259246/ 720p.m3u8"
  },
  {
   "type": "Highlight",
   "quality": "SD",
   "link": "https://m.topravideo.com:443/UpFiles/2023/7/26/42/259246/ 360p.m3u8"
  }
             ],
    "HomeImage": "https://i.ibb.co/D46m1WD/download-65.png",
    "HomeName": "Bayern",
    "Hot": "Hot",
    "LeagueImage": "https://www.flashscore.com/res/image/data/jiylaOkD-fHcB8pl5.png",
    "LeagueName": "Club Friendly",
    "LiveUpcoming": "‌Live",
    "Time": "1 - 2"
  },
  {
    "AwayImage": "https://i.ibb.co/6Xd01b7/download-9.png",
    "AwayName": "Tottenham",
    "Date": "July 26",
    "Link": [
  {
   "type": "Highlight",
   "quality": "HD",
   "link": "https://m.topravideo.com:443/UpFiles/2023/7/26/42/259255/ 720p.m3u8"
  },
  {
   "type": "Highlight",
   "quality": "SD",
   "link": "https://m.topravideo.com:443/UpFiles/2023/7/26/42/259255/ 360p.m3u8"
  }
             ],
    "HomeImage": "https://images.fotmob.com/image_resources/logo/teamlogo/67366.png",
    "HomeName": "Lion City Sailors FC",
    "Hot": "Hot",
    "LeagueImage": "https://www.flashscore.com/res/image/data/jiylaOkD-fHcB8pl5.png",
    "LeagueName": "Club Friendly",
    "LiveUpcoming": "Live",
    "Time": "1 - 5"
  },
  {
    "AwayImage": "https://i.ibb.co/v4DMkVK/download-2.png",
    "AwayName": "Manchester City",
    "Date": "July 23",
    "Link": [
  {
   "type": "Highlight",
   "quality": "HD",
   "link": "https://nlii.topravideo.com:443/UpFiles/2023/7/23/42/259116/ 720p.m3u8"
  },
  {
   "type": "Highlight",
   "quality": "SD",
   "link": "https://nlii.topravideo.com:443/UpFiles/2023/7/23/42/259116/ 360p.m3u8"
  }
             ],
    "HomeImage": "https://images.fotmob.com/image_resources/logo/teamlogo/6581.png",
    "HomeName": "Yokohama FM",
    "Hot": "Hot",
    "LeagueImage": "https://www.flashscore.com/res/image/data/jiylaOkD-fHcB8pl5.png",
    "LeagueName": "Club Friendly",
    "LiveUpcoming": "Upcoming",
    "Time": "4:30 PM"
  },
  {
    "AwayImage": "https://i.ibb.co/bN749H2/download-12.png",
    "AwayName": "Arsenal",
    "Date": "July 23",
    "Link": [
  {
   "type": "Highlight",
   "quality": "HD",
   "link": "https://nlii.topravideo.com:443/UpFiles/2023/7/23/42/259087/ 720p.m3u8"
  },
  {
   "type": "Highlights",
   "quality": "SD",
   "link": "https://nlii.topravideo.com:443/UpFiles/2023/7/23/42/259087/ 360p.m3u8"
  }
             ],
    "HomeImage": "https://i.ibb.co/rZFH50R/download-1.png",
    "HomeName": "Manchester United",
    "Hot": "Hot",
    "LeagueImage": "https://www.flashscore.com/res/image/data/jiylaOkD-fHcB8pl5.png",
    "LeagueName": "Club Friendly",
    "LiveUpcoming": "Upcoming",
    "Time": "2 - 0"
  },
  {
    "AwayImage": "https://i.ibb.co/RBH2X6r/download-13.png",
    "AwayName": "Brighton",
    "Date": "July 23",
    "Link": [
  {
   "type": "Highlight",
   "quality": "HD",
   "link": "https://nlii.topravideo.com:443/UpFiles/2023/7/23/42/259104/ 720p.m3u8"
  },
  {
   "type": "Highlights",
   "quality": "SD",
   "link": "https://nlii.topravideo.com:443/UpFiles/2023/7/23/42/259104/ 360p.m3u8"
  }
             ],
    "HomeImage": "https://i.ibb.co/MMN9Rw5/download.png",
    "HomeName": "Chelsea",
    "Hot": "Hot",
    "LeagueImage": "https://www.flashscore.com/res/image/data/jiylaOkD-fHcB8pl5.png",
    "LeagueName": "Club Friendly",
    "LiveUpcoming": "Upcoming",
    "Time": "4 - 3"
  }
]