[
 
 {
    "AwayImage": "https://i.ibb.co/Qjm2vQ9/download-33.png",
    "AwayName": "Espanyol",
    "Date": "December 31",
    "Hd1Link": "https://yypull.gdsth.com/live/stream-492306.m3u8?auth_key=1672511830-0-0-73ae0924e6dcec236c1f1d00aad1e96a",
    "Hd1Name": "China HD",
    "Hd2Link": "https://yypull.gdsth.com/live/stream-492306_ld.m3u8?auth_key=1672511830-0-0-147c5a1c0a24e337f325f082c0a39704",
    "Hd2Name": "China SD",
    "Hd3Link": "https://sports01.livnvess.com/live/stream-105131.m3u8?txSecret=29b1b6167a97aeb0a7c0494fd74fb8b2&txTime=63b08363",
    "Hd3Name": "Soco HD",
    "Hd4Link": "https://1123139281.cdn.khmer-hd.com/may3HD/playlist.m3u8",
    "Hd4Name": "Vebo HD",
    "Hd5Link": "https://standard-pull.qcllh.com/sm/10021_428408_lhd.flv?auth_key=1672576970-0-0-e47019ffeb8cd78d89f0ee3b51730bb1",
    "Hd5Name": "China 2SD",
    "Hd6Link": "https://standard-pull.qcllh.com/sm/10021_649422_lhd.flv?auth_key=1672576700-0-0-d4ca5664d8390bc71cedc4f8736bf8cd",
    "Hd6Name": "China 3SD",
    "HomeImage": "https://i.ibb.co/jh44yWL/download-66.png",
    "HomeName": "Barcelona",
    "Hot": "Hot",
    "LeagueName": "SPAIN - LA LIGA",
    "LiveNoti": "ကြည့်ရတာ ထစ်ခြင်း၊ကြည့်မရခြင်း များဖြစ်ပေါ်က ပြန်ထွက်၍ အခြား Quality ကိုရွေးချယ်ကြည့်ရှု ရန်အကြံပြုပါသည်။",
    "LiveUpcoming": "Live",
    "Time": "HD|SD"
  },
  {
    "AwayImage": "https://i.ibb.co/PF2LKYS/download-6.png",
    "AwayName": "Crystal Palace",
    "Date": "December 31",
    "Hd1Link": "https://yypull.gdsth.com/live/stream-279932.m3u8?auth_key=1672518850-0-0-deaec362d632d0cfdd4eb0fcccd76c9d",
    "Hd1Name": "China HD",
    "Hd2Link": "https://yypull.gdsth.com/live/stream-279932_ld.m3u8?auth_key=1672518850-0-0-38b80453595d343ae30e07af7d9195ec",
    "Hd2Name": "China SD",
    "Hd3Link": "0",
    "Hd3Name": "VN HD",
    "Hd4Link": "0",
    "Hd4Name": "VN SD",
    "Hd5Link": "0",
    "Hd5Name": "ENG",
    "Hd6Link": "0",
    "Hd6Name": "ENG",
    "HomeImage": "https://i.ibb.co/jfz7Sks/download-5.png",
    "HomeName": "Bournemouth",
    "Hot": "",
    "LeagueName": "PREMIER LEAGUE",
    "LiveNoti": "ကြည့်ရတာ ထစ်ခြင်း၊ကြည့်မရခြင်း များဖြစ်ပေါ်က ပြန်ထွက်၍ အခြား Quality ကိုရွေးချယ်ကြည့်ရှု ရန်အကြံပြုပါသည်။",
    "LiveUpcoming": "Live",
    "Time": "HD|SD"
  },
  {
    "AwayImage": "https://i.ibb.co/6XqKkjV/download-11.png",
    "AwayName": "Southampton",
    "Date": "December 31",
    "Hd1Link": "https://yytcpull.gdsth.com/live/stream-553612.m3u8?txSecret=1fbcfceb6ed5445e262cc27944caa786&txTime=63b199a6",
    "Hd1Name": "CN FHD",
    "Hd2Link": "https://yypull.gdsth.com/live/stream-349393_ld.m3u8?auth_key=1672518790-0-0-6de90595e79f6d2cb860ed06b649c6a5",
    "Hd2Name": "CN SD",
    "Hd3Link": "https://sports01.livnvess.com/live/stream-105131.m3u8?txSecret=9072d6a8783ce88f53643ae14a6fe082&txTime=63b099e3",
    "Hd3Name": "Soco HD",
    "Hd4Link": "0",
    "Hd4Name": "VN SD",
    "Hd5Link": "0",
    "Hd5Name": "ENG",
    "Hd6Link": "0",
    "Hd6Name": "ENG",
    "HomeImage": "https://i.ibb.co/8YZYVzF/download-15.png",
    "HomeName": "Fulham",
    "Hot": "Hot",
    "LeagueName": "PREMIER LEAGUE",
    "LiveNoti": "ကြည့်ရတာ ထစ်ခြင်း၊ကြည့်မရခြင်း များဖြစ်ပေါ်က ပြန်ထွက်၍ အခြား Quality ကိုရွေးချယ်ကြည့်ရှု ရန်အကြံပြုပါသည်။",
    "LiveUpcoming": "Live",
    "Time": "HD|SD"
  },
  {
    "AwayImage": "https://i.ibb.co/0VgNnHq/download-17.png",
    "AwayName": "Everton",
    "Date": "December 31",
    "Hd1Link": "https://yytcpull.gdsth.com/live/stream-482682.m3u8?txSecret=4625c039805672141b19d873af2f1bdb&txTime=63b1992e",
    "Hd1Name": "China HD",
    "Hd2Link": "https://yypull.gdsth.com/live/stream-286721_ld.m3u8?auth_key=1672518730-0-0-a8a159e9af75c3108708e0501cd9dc53",
    "Hd2Name": "China SD",
    "Hd3Link": "https://sports01.livnvess.com/live/stream-147801.m3u8?txSecret=3fac7c45858b217b43761ce8fab8b621&txTime=63b09a1f",
    "Hd3Name": "Soco HD",
    "Hd4Link": "https://1123139281.cdn.khmer-hd.com/may1HD/playlist.m3u8",
    "Hd4Name": "Vebo HD",
    "Hd5Link": "0",
    "Hd5Name": "ENG",
    "Hd6Link": "0",
    "Hd6Name": "ENG",
    "HomeImage": "https://i.ibb.co/v4DMkVK/download-2.png",
    "HomeName": "Manchester City",
    "Hot": "Hot",
    "LeagueName": "PREMIER LEAGUE",
    "LiveNoti": "ကြည့်ရတာ ထစ်ခြင်း၊ကြည့်မရခြင်း များဖြစ်ပေါ်က ပြန်ထွက်၍ အခြား Quality ကိုရွေးချယ်ကြည့်ရှု ရန်အကြံပြုပါသည်။",
    "LiveUpcoming": "Live",
    "Time": "HD|SD"
  },
  {
    "AwayImage": "https://i.ibb.co/0VRGgbR/download-16.png",
    "AwayName": "Leeds United",
    "Date": "December 31",
    "Hd1Link": "https://yypull.gdsth.com/live/stream-2412304.m3u8?auth_key=1672518610-0-0-7b7d4a13e3860443a8788a9b5db31744",
    "Hd1Name": "China HD",
    "Hd2Link": "https://yypull.gdsth.com/live/stream-2412304_ld.m3u8?auth_key=1672518610-0-0-167b08f17601891315b93151db7f42ab",
    "Hd2Name": "China SD",
    "Hd3Link": "https://sports01.livnvess.com/live/stream-143449.m3u8?txSecret=9d01497b24c2cb2f49bd43be7d3e6bad&txTime=63b09a5b",
    "Hd3Name": "Soco HD",
    "Hd4Link": "0",
    "Hd4Name": "VN SD",
    "Hd5Link": "0",
    "Hd5Name": "ENG",
    "Hd6Link": "0",
    "Hd6Name": "ENG",
    "HomeImage": "https://i.ibb.co/McsHxxG/download-4.png",
    "HomeName": "Newcastle",
    "Hot": "Hot",
    "LeagueName": "PREMIER LEAGUE",
    "LiveNoti": "ကြည့်ရတာ ထစ်ခြင်း၊ကြည့်မရခြင်း များဖြစ်ပေါ်က ပြန်ထွက်၍ အခြား Quality ကိုရွေးချယ်ကြည့်ရှု ရန်အကြံပြုပါသည်။",
    "LiveUpcoming": "Live",
    "Time": "HD|SD"
  },
  {
    "AwayImage": "https://i.ibb.co/mTH2ByB/download-28.png",
    "AwayName": "Osasuna",
    "Date": "December 31",
    "Hd1Link": "0",
    "Hd1Name": "CN FHD",
    "Hd2Link": "0",
    "Hd2Name": "CN SD",
    "Hd3Link": "0",
    "Hd3Name": "VN HD",
    "Hd4Link": "0",
    "Hd4Name": "VN SD",
    "Hd5Link": "0",
    "Hd5Name": "ENG",
    "Hd6Link": "0",
    "Hd6Name": "ENG",
    "HomeImage": "https://i.ibb.co/Px76w8v/download-27.png",
    "HomeName": "Real Sociedad",
    "Hot": "",
    "LeagueName": "SPAIN - LA LIGA",
    "LiveNoti": "ကြည့်ရတာ ထစ်ခြင်း၊ကြည့်မရခြင်း များဖြစ်ပေါ်က ပြန်ထွက်၍ အခြား Quality ကိုရွေးချယ်ကြည့်ရှု ရန်အကြံပြုပါသည်။",
    "LiveUpcoming": "Upcoming",
    "Time": "9:45 PM"
  },
  {
    "AwayImage": "https://i.ibb.co/LNsh3hr/download-34.png",
    "AwayName": "Valencia",
    "Date": "December 31",
    "Hd1Link": "0",
    "Hd1Name": "CN FHD",
    "Hd2Link": "0",
    "Hd2Name": "CN SD",
    "Hd3Link": "0",
    "Hd3Name": "VN HD",
    "Hd4Link": "0",
    "Hd4Name": "VN SD",
    "Hd5Link": "0",
    "Hd5Name": "ENG",
    "Hd6Link": "0",
    "Hd6Name": "ENG",
    "HomeImage": "https://i.ibb.co/7Vsf3Tg/download-21.png",
    "HomeName": "Villarreal",
    "Hot": "",
    "LeagueName": "SPAIN - LA LIGA",
    "LiveNoti": "ကြည့်ရတာ ထစ်ခြင်း၊ကြည့်မရခြင်း များဖြစ်ပေါ်က ပြန်ထွက်၍ အခြား Quality ကိုရွေးချယ်ကြည့်ရှု ရန်အကြံပြုပါသည်။",
    "LiveUpcoming": "Upcoming",
    "Time": "9:45 PM"
  },
  {
    "AwayImage": "https://i.ibb.co/bN749H2/download-12.png",
    "AwayName": "Arsenal",
    "Date": "January 01",
    "Hd1Link": "0",
    "Hd1Name": "CN FHD",
    "Hd2Link": "0",
    "Hd2Name": "CN SD",
    "Hd3Link": "0",
    "Hd3Name": "VN HD",
    "Hd4Link": "0",
    "Hd4Name": "VN SD",
    "Hd5Link": "0",
    "Hd5Name": "ENG",
    "Hd6Link": "0",
    "Hd6Name": "ENG",
    "HomeImage": "https://i.ibb.co/RBH2X6r/download-13.png",
    "HomeName": "Brighton",
    "Hot": "Hot",
    "LeagueName": "PREMIER LEAGUE",
    "LiveNoti": "ကြည့်ရတာ ထစ်ခြင်း၊ကြည့်မရခြင်း များဖြစ်ပေါ်က ပြန်ထွက်၍ အခြား Quality ကိုရွေးချယ်ကြည့်ရှု ရန်အကြံပြုပါသည်။",
    "LiveUpcoming": "Upcoming",
    "Time": "12:00 AM"
  }
]
